batchbook/__init__.py
batchbook/client.py
batchbook/exception.py
batchbook_python-0.1.1.dist-info/LICENSE
batchbook_python-0.1.1.dist-info/METADATA
batchbook_python-0.1.1.dist-info/WHEEL
batchbook_python-0.1.1.dist-info/RECORD
